CHANGES.rst
LICENSE.rst
MANIFEST.in
README.rst
buildout.cfg
requirements-4.3.x.txt
requirements-5.1.x.txt
requirements-5.2.x.txt
setup.py
test-4.3.x.cfg
test-5.1.x.cfg
test-5.2.x.cfg
src/souper/__init__.py
src/souper.plone.egg-info/PKG-INFO
src/souper.plone.egg-info/SOURCES.txt
src/souper.plone.egg-info/dependency_links.txt
src/souper.plone.egg-info/entry_points.txt
src/souper.plone.egg-info/namespace_packages.txt
src/souper.plone.egg-info/not-zip-safe
src/souper.plone.egg-info/requires.txt
src/souper.plone.egg-info/top_level.txt
src/souper/plone/__init__.py
src/souper/plone/configure.zcml
src/souper/plone/interfaces.py
src/souper/plone/locator.py
src/souper/plone/locator.rst
src/souper/plone/setuphandlers.py
src/souper/plone/testing.py
src/souper/plone/tests.py
src/souper/plone/browser/__init__.py
src/souper/plone/browser/admin.pt
src/souper/plone/browser/configure.zcml
src/souper/plone/browser/controlpanel.pt
src/souper/plone/browser/soupadministration.pt
src/souper/plone/browser/souper_icon.png
src/souper/plone/browser/views.py
src/souper/plone/profile/default/browserlayer.xml
src/souper/plone/profile/default/controlpanel.xml
src/souper/plone/profile/default/metadata.xml
src/souper/plone/profile/uninstall/browserlayer.xml
src/souper/plone/profile/uninstall/controlpanel.xml