Metadata-Version: 2.1
Name: souper.plone
Version: 1.3.1
Summary: Plone Souper Integration: Container for many lightweight queryable Records
Home-page: http://pypi.python.org/pypi/souper.plone
Author: BlueDynamics Alliance
Author-email: dev@bluedynamics.com
License: BSD
Keywords: container data record catalog
Platform: UNKNOWN
Classifier: Development Status :: 5 - Production/Stable
Classifier: License :: OSI Approved :: BSD License
Classifier: Operating System :: OS Independent
Classifier: Programming Language :: Python
Classifier: Programming Language :: Python :: 2
Classifier: Programming Language :: Python :: 2.7
Classifier: Programming Language :: Python :: 3
Classifier: Programming Language :: Python :: 3.6
Classifier: Programming Language :: Python :: 3.7
Classifier: Framework :: Zope :: 2
Classifier: Framework :: Zope :: 4
Classifier: Framework :: Plone :: 4.3
Classifier: Framework :: Plone :: 5.0
Classifier: Framework :: Plone :: 5.1
Classifier: Framework :: Plone :: 5.2
Classifier: Framework :: Plone :: Addon
Classifier: Intended Audience :: Developers
Classifier: Topic :: Software Development :: Libraries :: Python Modules
Provides-Extra: test
